kk_plugins/__init__.py
kk_plugins/account.py
kk_plugins/cmd.py
kk_plugins/compress.py
kk_plugins/excel.py
kk_plugins/project.py
kk_plugins/split_pdf.py
kk_plugins-0.1.240702.1.dist-info/METADATA
kk_plugins-0.1.240702.1.dist-info/WHEEL
kk_plugins-0.1.240702.1.dist-info/top_level.txt
kk_plugins-0.1.240702.1.dist-info/RECORD
