Metadata-Version: 2.1
Name: kk-plugins
Version: 0.1.240702.1
Summary: kk plugins
Home-page: https://github.com/kk-plugins
License: MIT
Keywords: kk-plugins
Classifier: Development Status :: 4 - Beta
Classifier: Intended Audience :: Developers
Classifier: License :: OSI Approved :: MIT License
Classifier: Natural Language :: English
Classifier: Programming Language :: Python :: 3
Classifier: Programming Language :: Python :: 3.7
Classifier: Programming Language :: Python :: 3.8
Classifier: Programming Language :: Python :: 3.9
Classifier: Programming Language :: Python :: 3.10
Requires-Dist: redis ~=4.5.4
Requires-Dist: requests ~=2.28.1
Requires-Dist: pandas ~=1.5.3
Requires-Dist: prettytable ~=3.8.0
Requires-Dist: Jinja2 ~=3.1.2
Requires-Dist: setuptools ~=60.2.0
Requires-Dist: xlwings
Requires-Dist: PyPDF2
